asset_model_data_storage/__init__.py
asset_model_data_storage/data_storage_handler.py
asset_model_data_storage/data_storage_service.py
asset_model_data_storage/s3_data_storage_service.py
asset_model_data_storage/system_data_storage_service.py
asset_model_data_storage-1.0.2.dist-info/licenses/LICENSE
tests/__init__.py
tests/test_data_storage_handler.py
tests/test_data_storage_service.py
tests/test_s3_data_storage_service.py
tests/test_system_data_storage_service.py
asset_model_data_storage-1.0.2.dist-info/METADATA
asset_model_data_storage-1.0.2.dist-info/WHEEL
asset_model_data_storage-1.0.2.dist-info/top_level.txt
asset_model_data_storage-1.0.2.dist-info/RECORD
