Metadata-Version: 2.4
Name: asset-model-data-storage
Version: 1.0.2
Summary: Data storage library for asset model apps
Author: Manoel Silva
License: MIT License
Project-URL: Homepage, https://github.com/ManoelSilva/asset-model-data-storage
Requires-Python: >=3.7
License-File: LICENSE
Requires-Dist: boto3
Requires-Dist: botocore
Provides-Extra: test
Requires-Dist: pytest; extra == "test"
Dynamic: license-file
